astro_otter-1.0.0.dist-info/licenses/LICENSE
otter/__init__.py
otter/_version.py
otter/exceptions.py
otter/schema.py
otter/util.py
otter/io/__init__.py
otter/io/data_finder.py
otter/io/host.py
otter/io/otter.py
otter/io/transient.py
otter/plotter/__init__.py
otter/plotter/otter_plotter.py
otter/plotter/plotter.py
astro_otter-1.0.0.dist-info/METADATA
astro_otter-1.0.0.dist-info/WHEEL
astro_otter-1.0.0.dist-info/top_level.txt
astro_otter-1.0.0.dist-info/RECORD
