Metadata-Version: 2.4
Name: astro-otter
Version: 1.0.0
Author-email: Noah Franz <nfranz@arizona.edu>
License: MIT License
Project-URL: Home, https://github.com/astro-otter
Classifier: License :: OSI Approved :: BSD License
Classifier: Topic :: Scientific/Engineering
Classifier: Intended Audience :: Science/Research
Classifier: Intended Audience :: Developers
Classifier: Operating System :: OS Independent
Classifier: License :: OSI Approved :: BSD License
Classifier: Programming Language :: Python
Classifier: Programming Language :: Python :: 3
Classifier: Programming Language :: Python :: 3.10
Classifier: Programming Language :: Python :: 3.11
Classifier: Development Status :: 2 - Pre-Alpha
Requires-Python: >=3.9
License-File: LICENSE
Requires-Dist: numpy<2,>=1.20
Requires-Dist: astropy>=6
Requires-Dist: pandas
Requires-Dist: synphot
Requires-Dist: typing-extensions
Requires-Dist: pyarango
Requires-Dist: tabulate
Requires-Dist: matplotlib
Requires-Dist: plotly
Requires-Dist: astroquery
Requires-Dist: ads
Requires-Dist: skypatrol
Requires-Dist: fundamentals
Requires-Dist: astro-datalab
Requires-Dist: sparclclient
Requires-Dist: pydantic>=2
Requires-Dist: dustmaps
Requires-Dist: dust_extinction
Requires-Dist: pyreadline3; platform_system == "Windows"
Provides-Extra: docs
Requires-Dist: Sphinx>=3.0.0; extra == "docs"
Requires-Dist: myst-parser>=0.13; extra == "docs"
Requires-Dist: nbsphinx>=0.9.1; extra == "docs"
Requires-Dist: sphinx-book-theme>=0.0.33; extra == "docs"
Requires-Dist: sphinx_copybutton; extra == "docs"
Requires-Dist: autodoc; extra == "docs"
Requires-Dist: ipykernel; extra == "docs"
Requires-Dist: autodoc_pydantic; extra == "docs"
Provides-Extra: dev
Requires-Dist: ruff; extra == "dev"
Requires-Dist: pre-commit; extra == "dev"
Requires-Dist: pytest-timeout; extra == "dev"
Requires-Dist: python-semantic-release; extra == "dev"
Dynamic: license-file
